dataaggregation/__init__.py
dataaggregation/aggregation.py
dataaggregation/lstm_anomly_detection.py
python_storage_timeline_ta_indicators-0.1.dist-info/METADATA
python_storage_timeline_ta_indicators-0.1.dist-info/WHEEL
python_storage_timeline_ta_indicators-0.1.dist-info/top_level.txt
python_storage_timeline_ta_indicators-0.1.dist-info/RECORD
