Metadata-Version: 2.1
Name: python-storage-timeline-ta-indicators
Version: 0.1
Summary: Tool to calculate technical analysis indicators in a continuous time series data
Home-page: https://github.com/C1l1r/python_storage_timeline_ta_indicators
Author: Oleksandr Namchuk
Author-email: c1l1rua@gmail.com
Requires-Dist: plotly
Requires-Dist: numpy
Requires-Dist: pandas
Requires-Dist: ta-lib
Requires-Dist: pandas-ta
Requires-Dist: tensorflow
Requires-Dist: matplotlib
Requires-Dist: seaborn
Requires-Dist: sklearn
